README.md
setup.py
django_nacos/__init__.py
django_nacos/client.py
django_nacos/commons.py
django_nacos/configer.py
django_nacos/exception.py
django_nacos/files.py
django_nacos/params.py
django_nacos.egg-info/PKG-INFO
django_nacos.egg-info/SOURCES.txt
django_nacos.egg-info/dependency_links.txt
django_nacos.egg-info/top_level.txt