Metadata-Version: 2.1
Name: django_nacos
Version: 0.1.2
Summary: Python client for Nacos.
Home-page: https://github.com/nacos-group/nacos-sdk-python
Author: nacos
Author-email: 755063194@qq.com
License: Apache License 2.0
Platform: UNKNOWN
